memory_buffer/MemLogging.py
memory_buffer/__init__.py
memory_buffer-0.0.1.dist-info/WHEEL
memory_buffer-0.0.1.dist-info/METADATA
memory_buffer-0.0.1.dist-info/RECORD
