Metadata-Version: 2.1
Name: memory-buffer
Version: 0.0.1
Summary: This module will let you write debug messages into a 500MB memory buffer which is Circular.
Home-page: https://github.com/sbalasa/MemoryBuffer.git
Author: Santhosh Balasa
Author-email: santhosh.kbr@gmail.com
Requires-Python: >=3.7,<4.0
Classifier: Programming Language :: Python :: 3
Classifier: Programming Language :: Python :: 3.7
Classifier: Programming Language :: Python :: 3.8
Classifier: Programming Language :: Python :: 3.9
